ZaiDiedai1Zhiqian/README.md
ZaiDiedai1Zhiqian/__init__.py
ZaiDiedai1Zhiqian/__main__.py
ZaiDiedai1Zhiqian/file.epub
ZaiDiedai1Zhiqian/index.html
ZaiDiedai1Zhiqian/css/__init__.py
ZaiDiedai1Zhiqian/css/annotations.css
ZaiDiedai1Zhiqian/css/main.css
ZaiDiedai1Zhiqian/css/normalize.css
ZaiDiedai1Zhiqian/css/popup.css
ZaiDiedai1Zhiqian/font/__init__.py
ZaiDiedai1Zhiqian/font/fontello.eot
ZaiDiedai1Zhiqian/font/fontello.svg
ZaiDiedai1Zhiqian/font/fontello.ttf
ZaiDiedai1Zhiqian/font/fontello.woff
ZaiDiedai1Zhiqian/img/__init__.py
ZaiDiedai1Zhiqian/img/annotator-glyph-sprite.png
ZaiDiedai1Zhiqian/img/annotator-icon-sprite.png
ZaiDiedai1Zhiqian/img/apple-touch-icon.png
ZaiDiedai1Zhiqian/img/cancelfullscreen.png
ZaiDiedai1Zhiqian/img/close.png
ZaiDiedai1Zhiqian/img/fullscreen.png
ZaiDiedai1Zhiqian/img/loader.gif
ZaiDiedai1Zhiqian/img/menu-icon.png
ZaiDiedai1Zhiqian/img/save.png
ZaiDiedai1Zhiqian/img/saved.png
ZaiDiedai1Zhiqian/img/settings-s.png
ZaiDiedai1Zhiqian/img/settings.png
ZaiDiedai1Zhiqian/img/star.png
ZaiDiedai1Zhiqian/js/__init__.py
ZaiDiedai1Zhiqian/js/epub.js
ZaiDiedai1Zhiqian/js/epub.min.js
ZaiDiedai1Zhiqian/js/epub.min.map
ZaiDiedai1Zhiqian/js/hooks.min.js
ZaiDiedai1Zhiqian/js/hooks.min.map
ZaiDiedai1Zhiqian/js/reader.js
ZaiDiedai1Zhiqian/js/reader.js.map
ZaiDiedai1Zhiqian/js/reader.min.js
ZaiDiedai1Zhiqian/js/reader.min.map
ZaiDiedai1Zhiqian/js/hooks/__init__.py
ZaiDiedai1Zhiqian/js/hooks/extensions/__init__.py
ZaiDiedai1Zhiqian/js/hooks/extensions/highlight.js
ZaiDiedai1Zhiqian/js/libs/__init__.py
ZaiDiedai1Zhiqian/js/libs/jquery.min.js
ZaiDiedai1Zhiqian/js/libs/localforage.min.js
ZaiDiedai1Zhiqian/js/libs/screenfull.js
ZaiDiedai1Zhiqian/js/libs/screenfull.min.js
ZaiDiedai1Zhiqian/js/libs/zip.min.js
ZaiDiedai1Zhiqian/js/plugins/__init__.py
ZaiDiedai1Zhiqian/js/plugins/hypothesis.js
ZaiDiedai1Zhiqian/js/plugins/search.js
zai_diedai_1_zhiqian-2024.3.3.0.dist-info/METADATA
zai_diedai_1_zhiqian-2024.3.3.0.dist-info/WHEEL
zai_diedai_1_zhiqian-2024.3.3.0.dist-info/entry_points.txt
zai_diedai_1_zhiqian-2024.3.3.0.dist-info/top_level.txt
zai_diedai_1_zhiqian-2024.3.3.0.dist-info/RECORD
